muhidinlib/__init__.py
muhidinlib/core.py
muhidinlib/modeling/__init__.py
muhidinlib/preprocessing/__init__.py
muhidinlib/visualization/__init__.py
muhidinlib/visualization/plot_utils.py
muhidinlib-0.1.1.dist-info/licenses/LICENSE
muhidinlib-0.1.1.dist-info/METADATA
muhidinlib-0.1.1.dist-info/WHEEL
muhidinlib-0.1.1.dist-info/top_level.txt
muhidinlib-0.1.1.dist-info/RECORD
