Metadata-Version: 2.4
Name: muhidinlib
Version: 0.1.1
Summary: "Utility Python sederhana yang sering digunakan dalam proyek data science."
Home-page: https://github.com/asepmuhidin
Author: Asep Muhidin
Author-email: asep.muhidin@pelitabangsa.ac.id
Classifier: Programming Language :: Python :: 3
Classifier: License :: OSI Approved :: MIT License
Requires-Python: >=3.6
License-File: LICENSE
Requires-Dist: pandas
Requires-Dist: matplotlib
Requires-Dist: seaborn
Requires-Dist: numpy
Requires-Dist: scipy
Dynamic: author
Dynamic: author-email
Dynamic: classifier
Dynamic: description
Dynamic: description-content-type
Dynamic: home-page
Dynamic: license-file
Dynamic: requires-dist
Dynamic: requires-python
Dynamic: summary
